barbicanclient/__init__.py
barbicanclient/_i18n.py
barbicanclient/barbican.py
barbicanclient/base.py
barbicanclient/client.py
barbicanclient/exceptions.py
barbicanclient/formatter.py
barbicanclient/osc_plugin.py
barbicanclient/version.py
barbicanclient/barbican_cli/__init__.py
barbicanclient/barbican_cli/v1/__init__.py
barbicanclient/barbican_cli/v1/acls.py
barbicanclient/barbican_cli/v1/cas.py
barbicanclient/barbican_cli/v1/containers.py
barbicanclient/barbican_cli/v1/orders.py
barbicanclient/barbican_cli/v1/secrets.py
barbicanclient/tests/__init__.py
barbicanclient/tests/keystone_client_fixtures.py
barbicanclient/tests/test_barbican.py
barbicanclient/tests/test_base.py
barbicanclient/tests/test_client.py
barbicanclient/tests/test_formatter.py
barbicanclient/tests/utils.py
barbicanclient/tests/v1/__init__.py
barbicanclient/tests/v1/test_acls.py
barbicanclient/tests/v1/test_cas.py
barbicanclient/tests/v1/test_consumers.py
barbicanclient/tests/v1/test_containers.py
barbicanclient/tests/v1/test_orders.py
barbicanclient/tests/v1/test_secrets.py
barbicanclient/v1/__init__.py
barbicanclient/v1/acls.py
barbicanclient/v1/cas.py
barbicanclient/v1/client.py
barbicanclient/v1/containers.py
barbicanclient/v1/orders.py
barbicanclient/v1/secrets.py
python_barbicanclient-7.2.0.dist-info/AUTHORS
python_barbicanclient-7.2.0.dist-info/LICENSE
python_barbicanclient-7.2.0.dist-info/METADATA
python_barbicanclient-7.2.0.dist-info/WHEEL
python_barbicanclient-7.2.0.dist-info/entry_points.txt
python_barbicanclient-7.2.0.dist-info/pbr.json
python_barbicanclient-7.2.0.dist-info/top_level.txt
python_barbicanclient-7.2.0.dist-info/RECORD
